{
    "Discards": [
        {"id": 0},
        {"id": 0},
        {"id": 1},
        {"id": 2},
        {"id": 31},
        {"id": 28},
        {"id": 30},
        {"id": 32},
        {"id": 29},
        {"id": 29},
        {"id": 9},
        {"id": 25},
        {"id": 29},
        {"id": 14},
        {"id": 0},
        {"id": 28},
        {"id": 32},
        {"id": 2},
        {"id": 4},
        {"id": 32},
        {"id": 28},
        {"id": 16},
        {"id": 20},
        {"id": 20},
        {"id": 30},
        {"id": 21},
        {"id": 14},
        {"id": 19},
        {"id": 29},
        {"id": 26},
        {"id": 15},
        {"id": 33},
        {"id": 20},
        {"id": 5},
        {"id": 25},
        {"id": 16},
        {"id": 28},
        {"id": 0},
        {"id": 20},
        {"id": 24},
        {"id": 0},
        {"id": 17},
        {"id": 10},
        {"id": 31},
        {"id": 3},
        {"id": 30},
        {"id": 4},
        {"id": 0},
        {"id": 18},
        {"id": 27},
        {"id": 32},
        {"id": 27},
        {"id": 3},
        {"id": 26},
        {"id": 2},
        {"id": 24},
        {"id": 25},
        {"id": 33},
        {"id": 8}
    ],
    "Hand": [
        {"id": 10},
        {"id": 10},
        {"id": 10},
        {"id": 11},
        {"id": 11},
        {"id": 23},
        {"id": 24},
        {"id": 25},
        {"id": 31},
        {"id": 31},
        {"id": 31},
        {"id": 33},
        {"id": 33},
        {"id": 33}
    ]
}